znp/__init__.py
znp/__main__.py
znp/options.py
znp/prompts.py
znp/utils.py
znp/zathura.py
znp/zsocket.py
znp-0.0.13.dist-info/LICENSE
znp-0.0.13.dist-info/METADATA
znp-0.0.13.dist-info/WHEEL
znp-0.0.13.dist-info/entry_points.txt
znp-0.0.13.dist-info/top_level.txt
znp-0.0.13.dist-info/RECORD
