Metadata-Version: 2.1
Name: znp
Version: 0.0.13
Summary: Simple program to open a file in existing zathura instance
License: GNU General Public License v3 (GPLv3)
Project-URL: repository, https://codeberg.org/johndovern/znp
Keywords: zathura
License-File: LICENSE
Requires-Dist: psutil
Requires-Dist: loadconf
Requires-Dist: promptx (>=0.0.5)
Provides-Extra: x11
Requires-Dist: ewmh ; extra == 'x11'
